{
    "inputs": [
      {
        "internalType": "uint256",
        "name": "gameId",
        "type": "uint256"
      }
    ],
    "name": "games",
    "outputs": [
      {
        "internalType": "uint256",
        "name": "accHeightPerKey1e18",
        "type": "uint256"
      },
      {
        "internalType": "uint128",
        "name": "keyPrice",
        "type": "uint128"
      },
      {
        "internalType": "uint128",
        "name": "startTimestamp",
        "type": "uint128"
      },
      {
        "internalType": "uint128",
        "name": "salesRevenue",
        "type": "uint128"
      },
      {
        "internalType": "uint128",
        "name": "totalKeyMinted",
        "type": "uint128"
      },
      {
        "internalType": "uint256",
        "name": "nftId",
        "type": "uint256"
      },
      {
        "internalType": "address",
        "name": "lastPlayer",
        "type": "address"
      },
      {
        "internalType": "address",
        "name": "nftAddress",
        "type": "address"
      },
      {
        "internalType": "address",
        "name": "principal",
        "type": "address"
      },
      {
        "internalType": "address",
        "name": "mostKeyBuyer",
        "type": "address"
      }
    ],
    "stateMutability": "view",
    "type": "function"
  }
  